pyporcc/__init__.py
pyporcc/click_converter.py
pyporcc/click_detector.py
pyporcc/data/__init__.py
pyporcc/data/standard_click.wav
pyporcc/models/__init__.py
pyporcc/models/log_models.ini
pyporcc/porcc.py
pyporcc/porpoise_classifier.py
pyporcc/utils.py
pyporcc-0.3.4.dist-info/LICENSE
pyporcc-0.3.4.dist-info/METADATA
pyporcc-0.3.4.dist-info/WHEEL
pyporcc-0.3.4.dist-info/RECORD
