Metadata-Version: 2.1
Name: pyporcc
Version: 0.3.4
Summary: 
Author: Clea Parcerisas
Requires-Python: >=3.10,<3.12.0
Classifier: Programming Language :: Python :: 3
Classifier: Programming Language :: Python :: 3.10
Classifier: Programming Language :: Python :: 3.11
Requires-Dist: h5py (>=3.11.0,<4.0.0)
Requires-Dist: matplotlib (>=3.9.2,<4.0.0)
Requires-Dist: numba (>=0.57.0,<0.58.0)
Requires-Dist: pandas (>=2.2.2,<3.0.0)
Requires-Dist: pyhydrophone (>=0.1.7)
Requires-Dist: scikit-learn (>=1.5.1,<2.0.0)
Requires-Dist: scipy (>=1.10.0)
Requires-Dist: tables (>=3.9.1,<4.0.0)
Requires-Dist: tqdm (>=4.66.5,<5.0.0)
